stash_data_mcp/server.py
stash_data_mcp-0.1.4.dist-info/METADATA
stash_data_mcp-0.1.4.dist-info/WHEEL
stash_data_mcp-0.1.4.dist-info/entry_points.txt
stash_data_mcp-0.1.4.dist-info/top_level.txt
stash_data_mcp-0.1.4.dist-info/RECORD
