Metadata-Version: 2.4
Name: stash-data-mcp
Version: 0.1.4
Summary: The ORM for AI Agents
Requires-Python: >=3.12
Requires-Dist: dotenv>=0.9.9
Requires-Dist: fastastra>=0.1.38
